pyOwlBoard/__init__.py
pyOwlBoard/client.py
pyOwlBoard/contants.py
pyOwlBoard/utils.py
pyOwlBoard/tests/__init__.py
pyOwlBoard-0.0.2.dist-info/LICENSE
pyOwlBoard-0.0.2.dist-info/METADATA
pyOwlBoard-0.0.2.dist-info/WHEEL
pyOwlBoard-0.0.2.dist-info/top_level.txt
pyOwlBoard-0.0.2.dist-info/RECORD
